jiracli/__init__.py
jiracli/tests/__init__.py
jiracli/tests/test_base.py
jiracli-0.4.7.dist-info/DESCRIPTION.rst
jiracli-0.4.7.dist-info/METADATA
jiracli-0.4.7.dist-info/RECORD
jiracli-0.4.7.dist-info/WHEEL
jiracli-0.4.7.dist-info/entry_points.txt
jiracli-0.4.7.dist-info/metadata.json
jiracli-0.4.7.dist-info/top_level.txt
