Metadata-Version: 2.0
Name: jiracli
Version: 0.4.7
Summary: command line interface for jira
Home-page: https://github.com/toabctl/jiracli
Author: Thomas Bechtold
Author-email: thomasbechtold@jpberlin.de
License: UNKNOWN
Platform: UNKNOWN
Classifier: Development Status :: 4 - Beta
Classifier: Environment :: Console
Classifier: License :: OSI Approved :: GNU General Public License v3 (GPLv3)
Classifier: License :: OSI Approved :: BSD License
Classifier: Programming Language :: Python
Classifier: Topic :: Software Development :: Bug Tracking
Classifier: Topic :: Utilities
Requires-Dist: jira (>=0.47)
Requires-Dist: pbr (>=0.6)
Requires-Dist: six
Requires-Dist: tabulate
Requires-Dist: termcolor
